{
  "type": "Feature",
  "stac_version": "1.0.0",
  "id": "VNP10A1.A2022097.h11v05.001.2022098094651",
  "properties": {
    "start_datetime": "2022-04-07T00:00:00Z",
    "end_datetime": "2022-04-07T23:59:59Z",
    "viirs:horizontal-tile": 11,
    "viirs:vertical-tile": 5,
    "viirs:tile-id": "51011005",
    "created": "2022-04-08T09:46:51Z",
    "platform": "Suomi National Polar-Orbiting Partnership (SNPP)",
    "proj:epsg": null,
    "proj:wkt2": "PROJCS[\"unnamed\",GEOGCS[\"Unknown datum based upon the custom spheroid\",DATUM[\"Not specified (based on custom spheroid)\",SPHEROID[\"Custom spheroid\",6371007.181,0]],PRIMEM[\"Greenwich\",0],UNIT[\"degree\",0.0174532925199433,AUTHORITY[\"EPSG\",\"9122\"]]],PROJECTION[\"Sinusoidal\"],PARAMETER[\"longitude_of_center\",0],PARAMETER[\"false_easting\",0],PARAMETER[\"false_northing\",0],UNIT[\"Meter\",1],AXIS[\"Easting\",EAST],AXIS[\"Northing\",NORTH]]",
    "proj:transform": [
      370.650173,
      0.0,
      -7783653.637667,
      0.0,
      -370.650173,
      4447802.078667
    ],
    "proj:shape": [
      3000,
      3000
    ],
    "datetime": null
  },
  "geometry": {
    "type": "Polygon",
    "coordinates": [
      [
        [
          -91.3785,
          40.0
        ],
        [
          -78.1106,
          40.054
        ],
        [
          -69.0368,
          29.892
        ],
        [
          -80.7658,
          29.8459
        ],
        [
          -91.3785,
          40.0
        ]
      ]
    ]
  },
  "links": [
    {
      "rel": "self",
      "href": "/Users/pjh/dev/viirs/examples/VNP10A1/VNP10A1.A2022097.h11v05.001.2022098094651.json",
      "type": "application/json"
    }
  ],
  "assets": {
    "hdf5": {
      "href": "../../tests/data-files/external/VNP10A1.A2022097.h11v05.001.2022098094651.h5",
      "type": "application/x-hdf5",
      "title": "Source data containing all bands",
      "roles": [
        "data"
      ]
    },
    "metadata": {
      "href": "../../tests/data-files/external/VNP10A1.A2022097.h11v05.001.2022098094651.h5.xml",
      "type": "application/xml",
      "title": "Earth Observing System Data and Information System (EOSDIS) metadata",
      "roles": [
        "metadata"
      ]
    }
  },
  "bbox": [
    -91.3785,
    29.8459,
    -69.0368,
    40.054
  ],
  "stac_extensions": [
    "https://stac-extensions.github.io/projection/v1.0.0/schema.json"
  ]
}